podnuit
